mercurygui/__init__.py
mercurygui/feed.py
mercurygui/main.py
mercurygui/main.ui
mercurygui/module_dialog.ui
mercurygui/panel.ui
mercurygui/pyqtplot_canvas.py
mercurygui/config/__init__.py
mercurygui/config/base.py
mercurygui/config/main.py
mercurygui/config/user.py
mercurygui/pyqt_labutils/__init__.py
mercurygui/pyqt_labutils/animated_widgets.py
mercurygui/pyqt_labutils/connection_dialog.py
mercurygui/pyqt_labutils/connection_dialog.ui
mercurygui/pyqt_labutils/dark_mode_support.py
mercurygui/pyqt_labutils/led_indicator.py
mercurygui/pyqt_labutils/list_entry_widget.py
mercurygui/pyqt_labutils/misc.py
mercurygui/pyqt_labutils/notify.py
mercurygui/pyqt_labutils/scientific_spinbox.py
mercurygui/pyqt_labutils/settings_pane.py
mercurygui/pyqt_labutils/spinner.py
mercurygui-3.0.3.dist-info/LICENSE.md
mercurygui-3.0.3.dist-info/METADATA
mercurygui-3.0.3.dist-info/WHEEL
mercurygui-3.0.3.dist-info/entry_points.txt
mercurygui-3.0.3.dist-info/top_level.txt
mercurygui-3.0.3.dist-info/RECORD
