Metadata-Version: 2.1
Name: mercurygui
Version: 3.0.3
Summary: A GUI to control the Oxford instruments Mercury iTC
Home-page: https://github.com/oe-fet/mercurygui.git
Author: Sam Schott
Author-email: ss2151@cam.ac.uk
License: MIT
Keywords: mercurygui
Platform: UNKNOWN
Classifier: License :: OSI Approved :: MIT License
Classifier: Operating System :: Unix
Classifier: Programming Language :: Python
Classifier: Programming Language :: Python :: 3.6
Classifier: Programming Language :: Python :: 3.7
Classifier: Programming Language :: Python :: 3.8
Classifier: Programming Language :: Python :: 3.9
Requires-Dist: pyvisa
Requires-Dist: mercuryitc (>=0.3.0)
Requires-Dist: numpy
Requires-Dist: pyqtgraph (>=0.11.0)
Requires-Dist: PyQt5
Requires-Dist: repr
Requires-Dist: setuptools
